Workbook

Sheet kinopoisk-top250
A1: rating | B1: movie | C1: year | D1: country | E1: rating_ball | F1: overview | G1: director | H1: screenwriter | I1: actors | J1: url_logo
A2: 0 | B2: Побег из Шоушенка | C2: 1994 | D2: США | E2: 9.111 | F2: Бухгалтер Энди Дюфрейн обвинён в убийстве собственной жены и её любовника. Оказавшись в тюрьме под названием Шоушенк; он сталкивается с жестокостью и беззаконием; царящими по обе стороны решётки. Каждый; кто попадает в эти стены; становится их рабом до конца жизни. Но Энди; обладающий живым умом и доброй душой; находит подход как к заключённым; так и к охранникам; добиваясь их особого к себе расположения. | G2: Фрэнк Дарабонт | H2: Фрэнк Дарабонт; Стивен Кинг | I2: Тим Роббинс; Морган Фриман; Боб Гантон; Уильям Сэдлер; Клэнси Браун | J2: 'https://st.kp.yandex.net/images/film_iphone/iphone360_326.jpg'
A3: 1 | B3: Зеленая миля | C3: 1999 | D3: США | E3: 9.062 | F3: Пол Эджкомб — начальник блока смертников в тюрьме «Холодная гора»; каждый из узников которого однажды проходит «зеленую милю» по пути к месту казни. Пол повидал много заключённых и надзирателей за время работы. Однако гигант Джон Коффи; обвинённый в страшном преступлении; стал одним из самых необычных обитателей блока. | G3: Фрэнк Дарабонт | H3: Фрэнк Дарабонт; Стивен Кинг | I3: Том Хэнкс; Дэвид Морс; Бонни Хант; Майкл Кларк Дункан; Джеймс Кромуэлл | J3: 'https://st.kp.yandex.net/images/film_iphone/iphone360_435.jpg'
A4: 2 | B4: Форрест Гамп | C4: 1994 | D4: США | E4: 8.913 | F4: От лица главного героя Форреста Гампа; слабоумного безобидного человека с благородным и открытым сердцем; рассказывается история его необыкновенной жизни.Фантастическим образом превращается он в известного футболиста; героя войны; преуспевающего бизнесмена. Он становится миллиардером; но остается таким же бесхитростным; глупым и добрым. Форреста ждет постоянный успех во всем; а он любит девочку; с которой дружил в детстве; но взаимность приходит слишком поздно. | G4: Роберт Земекис | H4: Эрик Рот; Уинстон Грум | I4: Том Хэнкс; Робин Райт; Салли Филд; Гэри Синиз; Майкелти Уильямсон | J4: 'https://st.kp.yandex.net/images/film_iphone/iphone360_448.jpg'
A5: 3 | B5: Список Шиндлера | C5: 1993 | D5: США | E5: 8.817 | F5: Фильм рассказывает реальную историю загадочного Оскара Шиндлера; члена нацистской партии; преуспевающего фабриканта; спасшего во время Второй мировой войны почти 1200 евреев. | G5: Стивен Спилберг | H5: Стивен Зеллиан; Томас Кенилли | I5: Лиам Нисон; Бен Кингсли; Рэйф Файнс; Кэролайн Гудолл; Эмбет Дэвидц | J5: 'https://st.kp.yandex.net/images/film_iphone/iphone360_329.jpg'
A6: 4 | B6: 1+1 | C6: 2011 | D6: Франция | E6: 8.807 | F6: Пострадав в результате несчастного случая; богатый аристократ Филипп нанимает в помощники человека; который менее всего подходит для этой работы; — молодого жителя предместья Дрисса; только что освободившегося из тюрьмы. Несмотря на то; что Филипп прикован к инвалидному креслу; Дриссу удается привнести в размеренную жизнь аристократа дух приключений. | G6: Оливье Накаш; Эрик Толедано | H6: Оливье Накаш; Филипп Поццо ди Борго; Эрик Толедано | I6: Франсуа Клюзе; Омар Си; Анн Ле Ни; Одри Флеро; Жозефин де Мо | J6: 'https://st.kp.yandex.net/images/film_iphone/iphone360_535341.jpg'
A7: 5 | B7: Начало | C7: 2010 | D7: США | E7: 8.662 | F7: Кобб — талантливый вор; лучший из лучших в опасном искусстве извлечения: он крадет ценные секреты из глубин подсознания во время сна; когда человеческий разум наиболее уязвим. Редкие способности Кобба сделали его ценным игроком в привычном к предательству мире промышленного шпионажа; но они же превратили его в извечного беглеца и лишили всего; что он когда-либо любил. И вот у Кобба появляется шанс исправить ошибки. Его последнее дело может вернуть все назад; но для этого ему нужно совершить невозможное — инициацию. Вместо идеальной кражи Кобб и его команда спецов должны будут провернуть обратное. Теперь их задача — не украсть идею; а внедрить ее. Если у них получится; это и станет идеальным преступлением. Но никакое планирование или мастерство не могут подготовить команду к встрече с опасным противником; который; кажется; предугадывает каждый их ход. Врагом; увидеть которого мог бы лишь Кобб. | G7: Кристофер Нолан | H7: Кристофер Нолан | I7: Леонардо ДиКаприо; Джозеф Гордон-Левитт; Эллен Пейдж; Том Харди; Кэн Ватанабэ | J7: 'https://st.kp.yandex.net/images/film_iphone/iphone360_447301.jpg'
A8: 6 | B8: Леон | C8: 1994 | D8: Франция | E8: 8.681 | F8: Профессиональный убийца Леон; не знающий пощады и жалости; знакомится со своей очаровательной соседкой Матильдой; семью которой расстреливают полицейские; замешанные в торговле наркотиками. Благодаря этому знакомству он впервые испытывает чувство любви; но… | G8: Люк Бессон | H8: Люк Бессон | I8: Жан Рено; Гари Олдман; Натали Портман; Дэнни Айелло; Питер Эппел | J8: 'https://st.kp.yandex.net/images/film_iphone/iphone360_389.jpg'
A9: 7 | B9: Король Лев | C9: 1994 | D9: США | E9: 8.772 | F9: У величественного Короля-Льва Муфасы рождается наследник по имени Симба. Уже в детстве любознательный малыш становится жертвой интриг своего завистливого дяди Шрама; мечтающего о власти.Симба познаёт горе утраты; предательство и изгнание; но в конце концов обретает верных друзей и находит любимую. Закалённый испытаниями; он в нелёгкой борьбе отвоёвывает своё законное место в «Круге жизни»; осознав; что значит быть настоящим Королём. | G9: Роджер Аллерс; Роб Минкофф | H9: Ирен Меччи; Джонатан Робертс; Линда Вулвертон; ... | I9: Мэттью Бродерик; Джереми Айронс; Нэйтан Лейн; Эрни Сабелла; Джеймс Эрл Джонс | J9: 'https://st.kp.yandex.net/images/film_iphone/iphone360_2360.jpg'
A10: 8 | B10: Бойцовский клуб | C10: 1999 | D10: США | E10: 8.645 | F10: Сотрудник страховой компании страдает хронической бессонницей и отчаянно пытается вырваться из мучительно скучной жизни. Однажды в очередной командировке он встречает некоего Тайлера Дёрдена — харизматического торговца мылом с извращенной философией. Тайлер уверен; что самосовершенствование — удел слабых; а единственное; ради чего стоит жить — саморазрушение.Проходит немного времени; и вот уже новые друзья лупят друг друга почем зря на стоянке перед баром; и очищающий мордобой доставляет им высшее блаженство. Приобщая других мужчин к простым радостям физической жестокости; они основывают тайный Бойцовский клуб; который начинает пользоваться невероятной популярностью. | G10: Дэвид Финчер | H10: Джим Улс; Чак Паланик | I10: Эдвард Нортон; Брэд Питт; Хелена Бонем Картер; Мит Лоаф; Зэк Гренье | J10: 'https://st.kp.yandex.net/images/film_iphone/iphone360_361.jpg'
A11: 9 | B11: Иван Васильевич меняет профессию | C11: 1973 | D11: СССР | E11: 8.782 | F11: Инженер-изобретатель Тимофеев сконструировал машину времени; которая соединила его квартиру с далеким шестнадцатым веком — точнее; с палатами государя Ивана Грозного. Туда-то и попадают тезка царя пенсионер-общественник Иван Васильевич Бунша и квартирный вор Жорж Милославский.На их место в двадцатом веке «переселяется» великий государь. Поломка машины приводит ко множеству неожиданных и забавных событий… | G11: Леонид Гайдай | H11: Владлен Бахнов; Леонид Гайдай; Михаил Булгаков | I11: Александр Демьяненко; Юрий Яковлев; Леонид Куравлёв; Наталья Крачковская; Савелий Крамаров | J11: 'https://st.kp.yandex.net/images/film_iphone/iphone360_42664.jpg'
A12: 10 | B12: Жизнь прекрасна | C12: 1997 | D12: Италия | E12: 8.624 | F12: Во время II Мировой войны в Италии в концлагерь были отправлены евреи; отец и его маленький сын. Жена; итальянка; добровольно последовала вслед за ними. В лагере отец сказал сыну; что все происходящее вокруг является очень большой игрой за приз в настоящий танк; который достанется тому мальчику; который сможет не попасться на глаза надзирателям. | G12: Роберто Бениньи | H12: Винченцо Черами; Роберто Бениньи | I12: Роберто Бениньи; Николетта Браски; Джорджио Кантарини; Джустино Дурано; Серджио Бини Бустрик | J12: 'https://st.kp.yandex.net/images/film_iphone/iphone360_381.jpg'
A13: 11 | B13: Достучаться до небес | C13: 1997 | D13: Германия | E13: 8.629 | F13: Судьба сводит героев картины в больнице; где врачи выносят им смертный приговор. Счет времени их жизней идет на часы. Дальнейшие события в фильме разворачиваются в стремительном темпе. Украв машину с миллионом немецких марок в багажнике; они сбегают из больницы.Их преследуют наемные убийцы; они становятся грабителями поневоле; за ними гонится полиция; они попадают в бордель. Но тем не менее продолжают мчаться вперед; навстречу своей судьбе. | G13: Томас Ян | H13: Томас Ян; Тиль Швайгер | I13: Тиль Швайгер; Ян Йозеф Лиферс; Тьерри Ван Вервеке; Мориц Бляйбтрой; Хуб Стапель | J13: 'https://st.kp.yandex.net/images/film_iphone/iphone360_32898.jpg'
... A251: 249 | B251: Холодное лето пятьдесят третьего... | C251: 1987 | D251: СССР | E251: 8.05 | F251: Двое бывших политзаключённых; недавно вышедших из лагеря; вступают в схватку с бандой амнистированных уголовников. Победу приходится оплатить дорогой ценой.Почти детективная история неравного поединка заканчивается и оптимистически; и трагически. Время действия — 1953 год; страна на пороге больших перемен… | G251: Александр Прошкин | H251: Эдгар Дубровский | I251: Валерий Приёмыхов; Анатолий Папанов; Виктор Степанов; Нина Усатова; Зоя Буряк | J251: 'https://st.kp.yandex.net/images/film_iphone/iphone360_7660.jpg'

Sheet Лист1
A2: =IF(AND(OR('kinopoisk-top250'!C2<1970,'kinopoisk-top250'!C2>1990),'kinopoisk-top250'!E2>8.5),'kinopoisk-top250'!G2," ") -> Фрэнк Дарабонт
A3: =IF(AND(OR('kinopoisk-top250'!C3<1970,'kinopoisk-top250'!C3>1990),'kinopoisk-top250'!E3>8.5),'kinopoisk-top250'!G3," ") -> Фрэнк Дарабонт
A4: =IF(AND(OR('kinopoisk-top250'!C4<1970,'kinopoisk-top250'!C4>1990),'kinopoisk-top250'!E4>8.5),'kinopoisk-top250'!G4," ") -> Роберт Земекис
A5: =IF(AND(OR('kinopoisk-top250'!C5<1970,'kinopoisk-top250'!C5>1990),'kinopoisk-top250'!E5>8.5),'kinopoisk-top250'!G5," ") -> Стивен Спилберг
A6: =IF(AND(OR('kinopoisk-top250'!C6<1970,'kinopoisk-top250'!C6>1990),'kinopoisk-top250'!E6>8.5),'kinopoisk-top250'!G6," ") -> Оливье Накаш; Эрик Толедано
A7: =IF(AND(OR('kinopoisk-top250'!C7<1970,'kinopoisk-top250'!C7>1990),'kinopoisk-top250'!E7>8.5),'kinopoisk-top250'!G7," ") -> Кристофер Нолан
A8: =IF(AND(OR('kinopoisk-top250'!C8<1970,'kinopoisk-top250'!C8>1990),'kinopoisk-top250'!E8>8.5),'kinopoisk-top250'!G8," ") -> Люк Бессон
A9: =IF(AND(OR('kinopoisk-top250'!C9<1970,'kinopoisk-top250'!C9>1990),'kinopoisk-top250'!E9>8.5),'kinopoisk-top250'!G9," ") -> Роджер Аллерс; Роб Минкофф
A10: =IF(AND(OR('kinopoisk-top250'!C10<1970,'kinopoisk-top250'!C10>1990),'kinopoisk-top250'!E10>8.5),'kinopoisk-top250'!G10," ") -> Дэвид Финчер
A11: =IF(AND(OR('kinopoisk-top250'!C11<1970,'kinopoisk-top250'!C11>1990),'kinopoisk-top250'!E11>8.5),'kinopoisk-top250'!G11," ")
A12: =IF(AND(OR('kinopoisk-top250'!C12<1970,'kinopoisk-top250'!C12>1990),'kinopoisk-top250'!E12>8.5),'kinopoisk-top250'!G12," ") -> Роберто Бениньи
A13: =IF(AND(OR('kinopoisk-top250'!C13<1970,'kinopoisk-top250'!C13>1990),'kinopoisk-top250'!E13>8.5),'kinopoisk-top250'!G13," ") -> Томас Ян
... A251: =IF(AND(OR('kinopoisk-top250'!C251<1970,'kinopoisk-top250'!C251>1990),'kinopoisk-top250'!E251>8.5),'kinopoisk-top250'!G251," ")
